memex/__init__.py
memex/bootstrap.py
memex/cli.py
memex/types.py
memex-0.1.0a287.dist-info/METADATA
memex-0.1.0a287.dist-info/WHEEL
memex-0.1.0a287.dist-info/entry_points.txt
memex-0.1.0a287.dist-info/RECORD
