Metadata-Version: 2.1
Name: memex
Version: 0.1.0a287
Summary: Memex API client
Home-page: https://www.memexdata.com/
License: Proprietary
Author: Memex
Author-email: dev@memexdata.com
Requires-Python: >=3.10,<4.0
Classifier: License :: Other/Proprietary License
Classifier: Programming Language :: Python :: 3
Classifier: Programming Language :: Python :: 3.10
Classifier: Programming Language :: Python :: 3.11
Classifier: Programming Language :: Python :: 3.12
Requires-Dist: dill (>=0.3.8,<0.4.0)
Requires-Dist: pandas (>=2.1.0,<3.0.0)
Requires-Dist: pydantic (>=2.0.0)
Requires-Dist: requests (>=2.27.1)
